{
  "sounds":[
  ],
  "labels":[
    {
      "pitchKnob":"<None>",
      "loop":0.0,
      "stack":"<None>",
      "gainOption":"Multiply",
      "persistentOption":"Unset",
      "pitchOption":"Unset",
      "transpose":[
        0.0,
        0.0
      ],
      "loopOption":"Unset",
      "persistent":null,
      "stackOption":"Unset",
      "name":"Test",
      "effectChain":"<None>",
      "gain":[
        1.2050000429153442,
        1.2050000429153442
      ],
      "transposeKnobOverride":0.0,
      "pitch":[
        1.0,
        1.0
      ],
      "effectChainOption":"Unset",
      "gainKnobOverride":0.0,
      "transposeKnob":"<None>",
      "pitchKnobOverride":0.0,
      "childArray":[
      ],
      "stackPriority":0.0,
      "gainKnob":"<None>",
      "transposeOption":"Unset"
    },
    {
      "pitchKnob":"<None>",
      "loop":0.0,
      "stack":"<None>",
      "gainOption":"Randomize",
      "persistentOption":"Unset",
      "pitchOption":"Unset",
      "transpose":[
        0.0,
        0.0
      ],
      "loopOption":"Unset",
      "persistent":null,
      "stackOption":"Unset",
      "name":"Unnamed Label 1",
      "effectChain":"<None>",
      "gain":[
        0.89999997615814209,
        1.0
      ],
      "transposeKnobOverride":0.0,
      "pitch":[
        1.0,
        1.0
      ],
      "effectChainOption":"Unset",
      "gainKnobOverride":0.0,
      "transposeKnob":"<None>",
      "pitchKnobOverride":0.0,
      "childArray":[
      ],
      "stackPriority":0.0,
      "gainKnob":"<None>",
      "transposeOption":"Unset"
    }
  ],
  "effectChains":[
  ],
  "patterns":[
    {
      "pitchKnob":"<None>",
      "sound":"sndBleep10",
      "bpm":120.0,
      "loop":false,
      "stack":"<None>",
      "gainOption":"Multiply",
      "persistentOption":"Unset",
      "pitchOption":"Unset",
      "transpose":[
        0.0,
        0.0
      ],
      "bpmOption":"Unset",
      "loopOption":"Unset",
      "persistent":null,
      "stackOption":"Unset",
      "name":"sndBleep10",
      "effectChain":"<None>",
      "gain":[
        1.1579999923706055,
        1.1579999923706055
      ],
      "type":"Sound",
      "transposeKnobOverride":false,
      "loopPoints":[
        0.0,
        0.0
      ],
      "pitch":[
        1.0,
        1.0
      ],
      "labels":[
      ],
      "effectChainOption":"Unset",
      "gainKnobOverride":false,
      "transposeKnob":"<None>",
      "loopPointsOption":"Unset",
      "pitchKnobOverride":false,
      "labelsOption":"Unset",
      "stackPriority":0.0,
      "gainKnob":"<None>",
      "transposeOption":"Unset"
    },
    {
      "pitchKnob":"<None>",
      "loop":0.0,
      "stack":"<None>",
      "gainOption":"Unset",
      "persistentOption":"Unset",
      "pitchOption":"Unset",
      "transpose":[
        0.0,
        0.0
      ],
      "loopOption":"Unset",
      "persistent":null,
      "stackOption":"Unset",
      "name":"Fallback",
      "effectChain":"<None>",
      "gain":[
        1.0,
        1.0
      ],
      "type":"Fallback",
      "transposeKnobOverride":0.0,
      "pitch":[
        1.0,
        1.0
      ],
      "labels":[
        "A"
      ],
      "effectChainOption":"Unset",
      "gainKnobOverride":0.0,
      "transposeKnob":"<None>",
      "pitchKnobOverride":0.0,
      "labelsOption":"Add",
      "stackPriority":0.0,
      "gainKnob":"<None>",
      "transposeOption":"Unset"
    },
    {
      "pitchKnob":"<None>",
      "sound":"snd1KHz",
      "bpm":120.0,
      "loop":1.0,
      "stack":"<None>",
      "gainOption":"Knob",
      "persistentOption":"Unset",
      "pitchOption":"Knob",
      "transpose":[
        0.0,
        0.0
      ],
      "bpmOption":"Unset",
      "loopOption":"Set",
      "persistent":null,
      "stackOption":"Unset",
      "name":"snd1KHz",
      "effectChain":"<None>",
      "gain":[
        0.71299999952316284,
        0.71299999952316284
      ],
      "type":"Sound",
      "transposeKnobOverride":0.0,
      "loopPoints":[
        0.0,
        0.0
      ],
      "pitch":[
        1.0,
        1.0
      ],
      "labels":[
      ],
      "effectChainOption":"Unset",
      "gainKnobOverride":0.0,
      "transposeKnob":"<None>",
      "loopPointsOption":"Unset",
      "pitchKnobOverride":0.0,
      "labelsOption":"Unset",
      "stackPriority":0.0,
      "gainKnob":"<None>",
      "transposeOption":"Knob"
    }
  ],
  "knobs":[
  ],
  "stacks":[
  ],
  "settings":{
    "autogenerateMacros":1.0,
    "macroScriptName":"__VinylGeneratedMacros"
  }
}